mailman3_fedmsg_plugin/__init__.py
mailman3_fedmsg_plugin-1.0.1.dist-info/LICENSES/LGPL-3.0-or-later.txt
mailman3_fedmsg_plugin-1.0.1.dist-info/METADATA
mailman3_fedmsg_plugin-1.0.1.dist-info/WHEEL
mailman3_fedmsg_plugin-1.0.1.dist-info/RECORD
