Metadata-Version: 2.3
Name: mailman3-fedmsg-plugin
Version: 1.0.1
Summary: Emit fedora-messaging messages from Mailman 3
License: LGPL-3.0-or-later
Keywords: fedora,fedora-messaging
Author: Aurélien Bompard
Author-email: aurelien@bompard.org
Requires-Python: >=3.9,<4.0
Classifier: License :: OSI Approved :: GNU Lesser General Public License v3 or later (LGPLv3+)
Classifier: Programming Language :: Python :: 3
Classifier: Programming Language :: Python :: 3.9
Classifier: Programming Language :: Python :: 3.10
Classifier: Programming Language :: Python :: 3.11
Classifier: Programming Language :: Python :: 3.12
Classifier: Programming Language :: Python :: 3.13
Requires-Dist: backoff (>=2.2.1,<3.0.0)
Requires-Dist: fedora-messaging (>=3.4.1,<4.0.0)
Requires-Dist: mailman (>=3.0.0)
Requires-Dist: mailman3-fedmsg-plugin-schemas (>=1.0.0)
Requires-Dist: zope-interface (>=6.2,<8.0.0)
Project-URL: Homepage, https://github.com/fedora-infra/mailman3-fedmsg-plugin
Project-URL: Repository, https://github.com/fedora-infra/mailman3-fedmsg-plugin
